my_favorite_things/__init__.py
my_favorite_things/colors.py
my_favorite_things/ddicts.py
my_favorite_things/plot.py
my_favorite_things/save.py
my_favorite_things-0.4.1.dist-info/LICENSE
my_favorite_things-0.4.1.dist-info/METADATA
my_favorite_things-0.4.1.dist-info/WHEEL
my_favorite_things-0.4.1.dist-info/top_level.txt
my_favorite_things-0.4.1.dist-info/RECORD
