Metadata-Version: 2.1
Name: my-favorite-things
Version: 0.4.1
Summary: Convenient functions and classes I use too often.
Author-email: Jacob Scott <jscott128@pm.me>
License: GNU GENERAL PUBLIC LICENSE
Project-URL: Github, https://github.com/crumpstrr33/my_favorite_things
Classifier: Intended Audience :: Developers
Classifier: Programming Language :: Python :: 3.10
Classifier: Programming Language :: Python :: 3.11
Classifier: Programming Language :: Python :: 3.12
Classifier: Operating System :: OS Independent
Classifier: License :: OSI Approved :: GNU General Public License v3 (GPLv3)
Requires-Python: >=3.10
License-File: LICENSE
Requires-Dist: numpy
Requires-Dist: matplotlib
Provides-Extra: dev
Requires-Dist: build ; extra == 'dev'
Requires-Dist: twine ; extra == 'dev'
Requires-Dist: black ; extra == 'dev'
Requires-Dist: isort ; extra == 'dev'
